frappymongocontent/__init__.py
frappymongocontent/content_store.py
frappymongocontent-1.0.1.dist-info/LICENSE
frappymongocontent-1.0.1.dist-info/METADATA
frappymongocontent-1.0.1.dist-info/WHEEL
frappymongocontent-1.0.1.dist-info/top_level.txt
frappymongocontent-1.0.1.dist-info/RECORD
