Metadata-Version: 2.1
Name: frappymongocontent
Version: 1.0.1
Summary: Store Implementation for Content in MongoDB
Home-page: https://github.com/ilfrich/frappy-py-mongo-content-store
Author: Peter Ilfrich
Author-email: das-peter@gmx.de
License: UNKNOWN
Platform: UNKNOWN
Requires-Dist: pbumongo (>=1.0.0)
